CHANGELOG.md
LICENSE
encrypted_model_fields/__init__.py
encrypted_model_fields/fields.py
encrypted_model_fields/management/__init__.py
encrypted_model_fields/management/commands/__init__.py
encrypted_model_fields/management/commands/generate_encryption_key.py
encrypted_model_fields/settings.py
encrypted_model_fields/tests.py
django_encrypted_model_fields-0.6.3.dist-info/LICENSE
django_encrypted_model_fields-0.6.3.dist-info/WHEEL
django_encrypted_model_fields-0.6.3.dist-info/METADATA
django_encrypted_model_fields-0.6.3.dist-info/RECORD
