Metadata-Version: 2.1
Name: django-encrypted-model-fields
Version: 0.6.3
Summary: A set of fields that wrap standard Django fields with encryption provided by the python cryptography library.
Home-page: https://gitlab.com/lansharkconsulting/django0-encrypted-model-fields
License: MIT
Keywords: encryption,django,fields
Author: Scott Sharkey
Author-email: ssharkey@lanshark.com
Requires-Python: >=3.6,<4.0
Classifier: Development Status :: 5 - Production/Stable
Classifier: Environment :: Web Environment
Classifier: Framework :: Django
Classifier: Framework :: Django :: 2.2
Classifier: Framework :: Django :: 3.0
Classifier: Framework :: Django :: 3.1
Classifier: Framework :: Django :: 3.2
Classifier: Framework :: Django :: 4.0
Classifier: Intended Audience :: Developers
Classifier: License :: OSI Approved :: MIT License
Classifier: Operating System :: OS Independent
Classifier: Operating System :: POSIX
Classifier: Operating System :: Unix
Classifier: Programming Language :: Python
Classifier: Programming Language :: Python :: 3
Classifier: Programming Language :: Python :: 3.10
Classifier: Programming Language :: Python :: 3.6
Classifier: Programming Language :: Python :: 3.7
Classifier: Programming Language :: Python :: 3.8
Classifier: Programming Language :: Python :: 3.9
Classifier: Topic :: Internet :: WWW/HTTP
Classifier: Topic :: Security
Classifier: Topic :: System :: Systems Administration :: Authentication/Directory
Requires-Dist: Django (>=2.2)
Requires-Dist: cryptography (>=3.4)
Project-URL: Repository, https://gitlab.com/lansharkconsulting/django0-encrypted-model-fields
